merlin_spectra/README
merlin_spectra/__init__.py
merlin_spectra/emission.py
merlin_spectra/galaxy_visualization.py
merlin_spectra/post.py
merlin_spectra/linelists/linelist.dat
merlin_spectra/linelists/linelist2.dat
merlin_spectra-0.0.4.dist-info/METADATA
merlin_spectra-0.0.4.dist-info/WHEEL
merlin_spectra-0.0.4.dist-info/licenses/LICENSE
merlin_spectra-0.0.4.dist-info/RECORD
