Metadata-Version: 2.4
Name: merlin-spectra
Version: 0.0.4
Summary: Interface with Cloudy Photoionization Software data and RAMSES-RT Simulation data to create galaxy images and spectra in nebular emission lines.
Project-URL: Homepage, https://github.com/BradenN6/Merlin
Author-email: Braden Nowicki <bnowicki@terpmail.umd.edu>
License-File: LICENSE
Keywords: JWST,astrophysics,spectra
Classifier: Intended Audience :: Science/Research
Classifier: Operating System :: OS Independent
Classifier: Programming Language :: Python :: 3
Classifier: Topic :: Scientific/Engineering :: Astronomy
Requires-Python: >=3.10
Requires-Dist: astropy>6.1
Requires-Dist: matplotlib>3.10
Requires-Dist: numpy>1.26
Requires-Dist: pandas>2.2
Requires-Dist: scipy>1.15
Requires-Dist: yt>4.4
